voronoi_cell/__init__.py
voronoi_cell/voronoi.py
voronoi_cell-0.0.3.dist-info/METADATA
voronoi_cell-0.0.3.dist-info/WHEEL
voronoi_cell-0.0.3.dist-info/licenses/LICENSE
voronoi_cell-0.0.3.dist-info/RECORD
